tina/Environment.py
tina/README.md
tina/__init__.py
tina/cli.py
tina/tina.py
tina/LLM/DeepSeek.py
tina/LLM/Qwen.py
tina/LLM/QwenVL.py
tina/LLM/__init__.py
tina/LLM/api.py
tina/LLM/llama.py
tina/MCP/Client.py
tina/MCP/MCPToolExecutor.py
tina/MCP/__init__.py
tina/agent/Agent.py
tina/agent/Character.py
tina/agent/__init__.py
tina/agent/core/__init__.py
tina/agent/core/error.py
tina/agent/core/executor.py
tina/agent/core/manage.py
tina/agent/core/parser.py
tina/agent/core/prompt.py
tina/agent/core/tools.py
tina/extend/__init__.py
tina/extend/hearing.py
tina/extend/multi-sourceInput.py
tina/utils/__init__.py
tina/utils/envReader.py
tina/utils/output_parser.py
tina/utils/systemTools.py
tina/utils/useBowser.py
tina_python-0.4.7.dist-info/METADATA
tina_python-0.4.7.dist-info/WHEEL
tina_python-0.4.7.dist-info/top_level.txt
tina_python-0.4.7.dist-info/RECORD
