Metadata-Version: 2.2
Name: tina-python
Version: 0.4.7
Summary: tina is in your computer!
Home-page: https://gitee.com/wang-churi/tina
Author: 王出日
Author-email: wangchuri@163.com
Classifier: Programming Language :: Python :: 3
Classifier: License :: OSI Approved :: Apache Software License
Classifier: Operating System :: OS Independent
Requires-Python: >=3.10
Requires-Dist: httpx
Requires-Dist: dotenv
Provides-Extra: mcp
Requires-Dist: mcp-python; extra == "mcp"
Dynamic: author
Dynamic: author-email
Dynamic: classifier
Dynamic: description
Dynamic: description-content-type
Dynamic: home-page
Dynamic: provides-extra
Dynamic: requires-dist
Dynamic: requires-python
Dynamic: summary
